{
  "parent": "item/generated",
  "textures": {
    "layer0": "growthcraft:item/cheddar"
  },
  "overrides": [
    { "predicate": { "cheese_state": -1 }, "model": "growthcraft:item/cheddar" },
    { "predicate": { "cheese_state": 0 }, "model": "growthcraft:item/cheddar" },
    { "predicate": { "cheese_state": 1 }, "model": "growthcraft:item/waxed_cheddar" },
    { "predicate": { "cheese_state": 2 }, "model": "growthcraft:item/waxed_cheddar" },
    { "predicate": { "cheese_state": 3 }, "model": "growthcraft:item/sliced_cheddar" }
  ]
}